README.md
setup.cfg
setup.py
jtt_tm_utils/__init__.py
jtt_tm_utils/consul_handle.py
jtt_tm_utils/kong.py
jtt_tm_utils/log.py
jtt_tm_utils/sync_basedata.py
jtt_tm_utils/timeutil.py
jtt_utils.egg-info/PKG-INFO
jtt_utils.egg-info/SOURCES.txt
jtt_utils.egg-info/dependency_links.txt
jtt_utils.egg-info/not-zip-safe
jtt_utils.egg-info/top_level.txt
tests/test_async.py
tests/test_class.py
tests/test_consul.py
tests/test_enum.py
tests/test_jtt_task.py
tests/test_kong.py
tests/test_log.py
tests/test_sync.py
tests/test_syncdata.py
tests/test_task.py